{
  "tracks": {
    "href":
      "https://api.spotify.com/v1/search?query=shut+up+and+dance&type=track&offset=0&limit=20",
    "items": [
      {
        "album": {
          "album_type": "album",
          "artists": [
            {
              "external_urls": {
                "spotify":
                  "https://open.spotify.com/artist/6DIS6PRrLS3wbnZsf7vYic"
              },
              "href":
                "https://api.spotify.com/v1/artists/6DIS6PRrLS3wbnZsf7vYic",
              "id": "6DIS6PRrLS3wbnZsf7vYic",
              "name": "WALK THE MOON",
              "type": "artist",
              "uri": "spotify:artist:6DIS6PRrLS3wbnZsf7vYic"
            }
          ],
          "available_markets": [
            "AD",
            "AR",
            "AT",
            "AU",
            "BE",
            "BG",
            "BO",
            "BR",
            "CA",
            "CH",
            "CL",
            "CO",
            "CR",
            "CY",
            "CZ",
            "DE",
            "DK",
            "DO",
            "EC",
            "EE",
            "ES",
            "FI",
            "FR",
            "GR",
            "GT",
            "HK",
            "HN",
            "HU",
            "ID",
            "IE",
            "IL",
            "IS",
            "IT",
            "JP",
            "LI",
            "LT",
            "LU",
            "LV",
            "MC",
            "MT",
            "MX",
            "MY",
            "NI",
            "NL",
            "NO",
            "NZ",
            "PA",
            "PE",
            "PH",
            "PL",
            "PT",
            "PY",
            "RO",
            "SE",
            "SG",
            "SK",
            "SV",
            "TH",
            "TR",
            "TW",
            "US",
            "UY",
            "VN",
            "ZA"
          ],
          "external_urls": {
            "spotify": "https://open.spotify.com/album/3mNoFlD1wsoXfkljfFzExT"
          },
          "href": "https://api.spotify.com/v1/albums/3mNoFlD1wsoXfkljfFzExT",
          "id": "3mNoFlD1wsoXfkljfFzExT",
          "images": [
            {
              "height": 640,
              "url":
                "https://i.scdn.co/image/1c87b0ac6f0cd837dc399d52bab96134442547ea",
              "width": 640
            },
            {
              "height": 300,
              "url":
                "https://i.scdn.co/image/fae75f376d3e7e076ccd714785cb76129b82a15f",
              "width": 300
            },
            {
              "height": 64,
              "url":
                "https://i.scdn.co/image/e27340225ed8416e779e693bc642e7b460a767e4",
              "width": 64
            }
          ],
          "name": "TALKING IS HARD",
          "release_date": "2014-11-24",
          "release_date_precision": "day",
          "type": "album",
          "uri": "spotify:album:3mNoFlD1wsoXfkljfFzExT"
        },
        "artists": [
          {
            "external_urls": {
              "spotify":
                "https://open.spotify.com/artist/6DIS6PRrLS3wbnZsf7vYic"
            },
            "href": "https://api.spotify.com/v1/artists/6DIS6PRrLS3wbnZsf7vYic",
            "id": "6DIS6PRrLS3wbnZsf7vYic",
            "name": "WALK THE MOON",
            "type": "artist",
            "uri": "spotify:artist:6DIS6PRrLS3wbnZsf7vYic"
          }
        ],
        "available_markets": [
          "AD",
          "AR",
          "AT",
          "AU",
          "BE",
          "BG",
          "BO",
          "BR",
          "CA",
          "CH",
          "CL",
          "CO",
          "CR",
          "CY",
          "CZ",
          "DE",
          "DK",
          "DO",
          "EC",
          "EE",
          "ES",
          "FI",
          "FR",
          "GR",
          "GT",
          "HK",
          "HN",
          "HU",
          "ID",
          "IE",
          "IL",
          "IS",
          "IT",
          "JP",
          "LI",
          "LT",
          "LU",
          "LV",
          "MC",
          "MT",
          "MX",
          "MY",
          "NI",
          "NL",
          "NO",
          "NZ",
          "PA",
          "PE",
          "PH",
          "PL",
          "PT",
          "PY",
          "RO",
          "SE",
          "SG",
          "SK",
          "SV",
          "TH",
          "TR",
          "TW",
          "US",
          "UY",
          "VN",
          "ZA"
        ],
        "disc_number": 1,
        "duration_ms": 199080,
        "explicit": false,
        "external_ids": { "isrc": "USRC11401949" },
        "external_urls": {
          "spotify": "https://open.spotify.com/track/4kbj5MwxO1bq9wjT5g9HaA"
        },
        "href": "https://api.spotify.com/v1/tracks/4kbj5MwxO1bq9wjT5g9HaA",
        "id": "4kbj5MwxO1bq9wjT5g9HaA",
        "is_local": false,
        "name": "Shut Up and Dance",
        "popularity": 80,
        "preview_url":
          "https://p.scdn.co/mp3-preview/50171ad2206e8f6b2ecad2266d353472427c358e?cid=cd2cbf7b258249d1b36e316ca7fee072",
        "track_number": 3,
        "type": "track",
        "uri": "spotify:track:4kbj5MwxO1bq9wjT5g9HaA"
      },
      {
        "album": {
          "album_type": "single",
          "artists": [
            {
              "external_urls": {
                "spotify":
                  "https://open.spotify.com/artist/6DIS6PRrLS3wbnZsf7vYic"
              },
              "href":
                "https://api.spotify.com/v1/artists/6DIS6PRrLS3wbnZsf7vYic",
              "id": "6DIS6PRrLS3wbnZsf7vYic",
              "name": "WALK THEMOON",
              "type": "artist",
              "uri": "spotify:artist:6DIS6PRrLS3wbnZsf7vYic"
            }
          ],
          "available_markets": [
            "AD",
            "AR",
            "AT",
            "AU",
            "BE",
            "BG",
            "BO",
            "BR",
            "CA",
            "CH",
            "CL",
            "CO",
            "CR",
            "CY",
            "CZ",
            "DE",
            "DK",
            "DO",
            "EC",
            "EE",
            "ES",
            "FI",
            "FR",
            "GB",
            "GR",
            "GT",
            "HK",
            "HN",
            "HU",
            "ID",
            "IE",
            "IL",
            "IS",
            "IT",
            "JP",
            "LI",
            "LT",
            "LU",
            "LV",
            "MC",
            "MT",
            "MX",
            "MY",
            "NI",
            "NL",
            "NO",
            "NZ",
            "PA",
            "PE",
            "PH",
            "PL",
            "PT",
            "PY",
            "RO",
            "SE",
            "SG",
            "SK",
            "SV",
            "TH",
            "TR",
            "TW",
            "US",
            "UY",
            "VN",
            "ZA"
          ],
          "external_urls": {
            "spotify": "https://open.spotify.com/album/7gVpldI2kuvncnrLtiOcDl"
          },
          "href": "https://api.spotify.com/v1/albums/7gVpldI2kuvncnrLtiOcDl",
          "id": "7gVpldI2kuvncnrLtiOcDl",
          "images": [
            {
              "height": 640,
              "url":
                "https://i.scdn.co/image/2da21a9e47d94472bff8ebdab61a6c134f61239a",
              "width": 640
            },
            {
              "height": 300,
              "url":
                "https://i.scdn.co/image/0ad2102548bec42f3325dd48e2c908e0c289e685",
              "width": 300
            },
            {
              "height": 64,
              "url":
                "https://i.scdn.co/image/2e06527c75066cce2462ed4a73988b1e656a100c",
              "width": 64
            }
          ],
          "name": "Shut Up And Dance (Acoustic)",
          "release_date": "2015-09-04",
          "release_date_precision": "day",
          "type": "album",
          "uri": "spotify:album:7gVpldI2kuvncnrLtiOcDl"
        },
        "artists": [
          {
            "external_urls": {
              "spotify":
                "https://open.spotify.com/artist/6DIS6PRrLS3wbnZsf7vYic"
            },
            "href": "https://api.spotify.com/v1/artists/6DIS6PRrLS3wbnZsf7vYic",
            "id": "6DIS6PRrLS3wbnZsf7vYic",
            "name": "WALK THE MOON",
            "type": "artist",
            "uri": "spotify:artist:6DIS6PRrLS3wbnZsf7vYic"
          }
        ],
        "available_markets": [
          "AD",
          "AR",
          "AT",
          "AU",
          "BE",
          "BG",
          "BO",
          "BR",
          "CA",
          "CH",
          "CL",
          "CO",
          "CR",
          "CY",
          "CZ",
          "DE",
          "DK",
          "DO",
          "EC",
          "EE",
          "ES",
          "FI",
          "FR",
          "GB",
          "GR",
          "GT",
          "HK",
          "HN",
          "HU",
          "ID",
          "IE",
          "IL",
          "IS",
          "IT",
          "JP",
          "LI",
          "LT",
          "LU",
          "LV",
          "MC",
          "MT",
          "MX",
          "MY",
          "NI",
          "NL",
          "NO",
          "NZ",
          "PA",
          "PE",
          "PH",
          "PL",
          "PT",
          "PY",
          "RO",
          "SE",
          "SG",
          "SK",
          "SV",
          "TH",
          "TR",
          "TW",
          "US",
          "UY",
          "VN",
          "ZA"
        ],
        "disc_number": 1,
        "duration_ms": 193986,
        "explicit": false,
        "external_ids": { "isrc": "USRC11501303" },
        "external_urls": {
          "spotify": "https://open.spotify.com/track/3Xzog9enTvbsc0G7G9M58D"
        },
        "href": "https://api.spotify.com/v1/tracks/3Xzog9enTvbsc0G7G9M58D",
        "id": "3Xzog9enTvbsc0G7G9M58D",
        "is_local": false,
        "name": "Shut Up and Dance - Live Acoustic",
        "popularity": 62,
        "preview_url":
          "https://p.scdn.co/mp3-preview/8c8e2befc12f85cf90c7a259a21f477fee09429f?cid=cd2cbf7b258249d1b36e316ca7fee072",
        "track_number": 1,
        "type": "track",
        "uri": "spotify:track:3Xzog9enTvbsc0G7G9M58D"
      },
      {
        "album": {
          "album_type": "single",
          "artists": [
            {
              "external_urls": {
                "spotify":
                  "https://open.spotify.com/artist/1mjqymUKo7KbLtvfYD386t"
              },
              "href":
                "https://api.spotify.com/v1/artists/1mjqymUKo7KbLtvfYD386t",
              "id": "1mjqymUKo7KbLtvfYD386t",
              "name": "Anchor + Bell",
              "type": "artist",
              "uri": "spotify:artist:1mjqymUKo7KbLtvfYD386t"
            }
          ],
          "available_markets": [
            "AD",
            "AR",
            "AT",
            "AU",
            "BE",
            "BG",
            "BO",
            "BR",
            "CA",
            "CH",
            "CL",
            "CO",
            "CR",
            "CY",
            "CZ",
            "DE",
            "DK",
            "DO",
            "EC",
            "EE",
            "ES",
            "FI",
            "FR",
            "GB",
            "GR",
            "GT",
            "HK",
            "HN",
            "HU",
            "ID",
            "IE",
            "IL",
            "IS",
            "IT",
            "JP",
            "LI",
            "LT",
            "LU",
            "LV",
            "MC",
            "MT",
            "MX",
            "MY",
            "NI",
            "NL",
            "NO",
            "NZ",
            "PA",
            "PE",
            "PH",
            "PL",
            "PT",
            "PY",
            "RO",
            "SE",
            "SG",
            "SK",
            "SV",
            "TH",
            "TR",
            "TW",
            "US",
            "UY",
            "VN",
            "ZA"
          ],
          "external_urls": {
            "spotify": "https://open.spotify.com/album/73nVNq34LtpDZmRHWV1fo0"
          },
          "href": "https://api.spotify.com/v1/albums/73nVNq34LtpDZmRHWV1fo0",
          "id": "73nVNq34LtpDZmRHWV1fo0",
          "images": [
            {
              "height": 640,
              "url":
                "https://i.scdn.co/image/1397f74fcffab502f623cbf88e774666983745a6",
              "width": 640
            },
            {
              "height": 300,
              "url":
                "https://i.scdn.co/image/c3fe3e8bb91cf20c28525fc20a285ebb1534595c",
              "width": 300
            },
            {
              "height": 64,
              "url":
                "https://i.scdn.co/image/697dcd442778dca970347d5f188a3c20a6e7f3f5",
              "width": 64
            }
          ],
          "name": "Shut up and Dance",
          "release_date": "2016-05-06",
          "release_date_precision": "day",
          "type": "album",
          "uri": "spotify:album:73nVNq34LtpDZmRHWV1fo0"
        },
        "artists": [
          {
            "external_urls": {
              "spotify":
                "https://open.spotify.com/artist/1mjqymUKo7KbLtvfYD386t"
            },
            "href": "https://api.spotify.com/v1/artists/1mjqymUKo7KbLtvfYD386t",
            "id": "1mjqymUKo7KbLtvfYD386t",
            "name": "Anchor + Bell",
            "type": "artist",
            "uri": "spotify:artist:1mjqymUKo7KbLtvfYD386t"
          }
        ],
        "available_markets": [
          "AD",
          "AR",
          "AT",
          "AU",
          "BE",
          "BG",
          "BO",
          "BR",
          "CA",
          "CH",
          "CL",
          "CO",
          "CR",
          "CY",
          "CZ",
          "DE",
          "DK",
          "DO",
          "EC",
          "EE",
          "ES",
          "FI",
          "FR",
          "GB",
          "GR",
          "GT",
          "HK",
          "HN",
          "HU",
          "ID",
          "IE",
          "IL",
          "IS",
          "IT",
          "JP",
          "LI",
          "LT",
          "LU",
          "LV",
          "MC",
          "MT",
          "MX",
          "MY",
          "NI",
          "NL",
          "NO",
          "NZ",
          "PA",
          "PE",
          "PH",
          "PL",
          "PT",
          "PY",
          "RO",
          "SE",
          "SG",
          "SK",
          "SV",
          "TH",
          "TR",
          "TW",
          "US",
          "UY",
          "VN",
          "ZA"
        ],
        "disc_number": 1,
        "duration_ms": 176182,
        "explicit": false,
        "external_ids": { "isrc": "TCACO1620657" },
        "external_urls": {
          "spotify": "https://open.spotify.com/track/7K9GqO7ciCHJe2bkoZoM5i"
        },
        "href": "https://api.spotify.com/v1/tracks/7K9GqO7ciCHJe2bkoZoM5i",
        "id": "7K9GqO7ciCHJe2bkoZoM5i",
        "is_local": false,
        "name": "Shut up and Dance",
        "popularity": 57,
        "preview_url":
          "https://p.scdn.co/mp3-preview/64fab5a912949fc60fdbdc470930a2951baa5a0f?cid=cd2cbf7b258249d1b36e316ca7fee072",
        "track_number": 1,
        "type": "track",
        "uri": "spotify:track:7K9GqO7ciCHJe2bkoZoM5i"
      },
      {
        "album": {
          "album_type": "album",
          "artists": [
            {
              "external_urls": {
                "spotify":
                  "https://open.spotify.com/artist/5BKzvAPtNXnt0LwzGvKOH3"
              },
              "href":
                "https://api.spotify.com/v1/artists/5BKzvAPtNXnt0LwzGvKOH3",
              "id": "5BKzvAPtNXnt0LwzGvKOH3",
              "name": "Aaron Watson",
              "type": "artist",
              "uri": "spotify:artist:5BKzvAPtNXnt0LwzGvKOH3"
            }
          ],
          "available_markets": ["CA", "US"],
          "external_urls": {
            "spotify": "https://open.spotify.com/album/0JLxbOIxLJ5oDqYLOxJlnM"
          },
          "href": "https://api.spotify.com/v1/albums/0JLxbOIxLJ5oDqYLOxJlnM",
          "id": "0JLxbOIxLJ5oDqYLOxJlnM",
          "images": [
            {
              "height": 640,
              "url":
                "https://i.scdn.co/image/8fe4b2d28e543128ccc13a7a2327f4f445963972",
              "width": 640
            },
            {
              "height": 300,
              "url":
                "https://i.scdn.co/image/330799dec4e7347e2d651a60cdbc8ac41c219d4c",
              "width": 300
            },
            {
              "height": 64,
              "url":
                "https://i.scdn.co/image/b8585a90df8e4067331a69cea7a775525f35795d",
              "width": 64
            }
          ],
          "name": "Shut up and Dance",
          "release_date": "2002",
          "release_date_precision": "year",
          "type": "album",
          "uri": "spotify:album:0JLxbOIxLJ5oDqYLOxJlnM"
        },
        "artists": [
          {
            "external_urls": {
              "spotify":
                "https://open.spotify.com/artist/5BKzvAPtNXnt0LwzGvKOH3"
            },
            "href": "https://api.spotify.com/v1/artists/5BKzvAPtNXnt0LwzGvKOH3",
            "id": "5BKzvAPtNXnt0LwzGvKOH3",
            "name": "Aaron Watson",
            "type": "artist",
            "uri": "spotify:artist:5BKzvAPtNXnt0LwzGvKOH3"
          }
        ],
        "available_markets": ["CA", "US"],
        "disc_number": 1,
        "duration_ms": 266306,
        "explicit": false,
        "external_ids": { "isrc": "US4AB0400005" },
        "external_urls": {
          "spotify": "https://open.spotify.com/track/5RFFWZNLyqmRruztuzyWHZ"
        },
        "href": "https://api.spotify.com/v1/tracks/5RFFWZNLyqmRruztuzyWHZ",
        "id": "5RFFWZNLyqmRruztuzyWHZ",
        "is_local": false,
        "name": "Shut up and Dance",
        "popularity": 39,
        "preview_url":
          "https://p.scdn.co/mp3-preview/2c2521a00c75e3a585b42770cf50046afc5b6356?cid=cd2cbf7b258249d1b36e316ca7fee072",
        "track_number": 5,
        "type": "track",
        "uri": "spotify:track:5RFFWZNLyqmRruztuzyWHZ"
      },
      {
        "album": {
          "album_type": "album",
          "artists": [
            {
              "external_urls": {
                "spotify":
                  "https://open.spotify.com/artist/1Vvvx45Apu6dQqwuZQxtgW"
              },
              "href":
                "https://api.spotify.com/v1/artists/1Vvvx45Apu6dQqwuZQxtgW",
              "id": "1Vvvx45Apu6dQqwuZQxtgW",
              "name": "Kidz Bop Kids",
              "type": "artist",
              "uri": "spotify:artist:1Vvvx45Apu6dQqwuZQxtgW"
            }
          ],
          "available_markets": ["US"],
          "external_urls": {
            "spotify": "https://open.spotify.com/album/3QNWZIE9VH4D1CkK14uXkX"
          },
          "href": "https://api.spotify.com/v1/albums/3QNWZIE9VH4D1CkK14uXkX",
          "id": "3QNWZIE9VH4D1CkK14uXkX",
          "images": [
            {
              "height": 640,
              "url":
                "https://i.scdn.co/image/6c411f5c2a6d868929e016cbcb14721f519806bf",
              "width": 640
            },
            {
              "height": 300,
              "url":
                "https://i.scdn.co/image/bfc065988da6b0db3c6fb2cbc6478084c52c9d4d",
              "width": 300
            },
            {
              "height": 64,
              "url":
                "https://i.scdn.co/image/184ca0b1de9e049cd39b22fef65d87f513185f2f",
              "width": 64
            }
          ],
          "name": "Kidz Bop 29",
          "release_date": "2015-07-10",
          "release_date_precision": "day",
          "type": "album",
          "uri": "spotify:album:3QNWZIE9VH4D1CkK14uXkX"
        },
        "artists": [
          {
            "external_urls": {
              "spotify":
                "https://open.spotify.com/artist/1Vvvx45Apu6dQqwuZQxtgW"
            },
            "href": "https://api.spotify.com/v1/artists/1Vvvx45Apu6dQqwuZQxtgW",
            "id": "1Vvvx45Apu6dQqwuZQxtgW",
            "name": "Kidz Bop Kids",
            "type": "artist",
            "uri": "spotify:artist:1Vvvx45Apu6dQqwuZQxtgW"
          }
        ],
        "available_markets": ["US"],
        "disc_number": 1,
        "duration_ms": 198306,
        "explicit": false,
        "external_ids": { "isrc": "USRZO1537908" },
        "external_urls": {
          "spotify": "https://open.spotify.com/track/7KqjPr2vj8CwQ1cV2swc57"
        },
        "href": "https://api.spotify.com/v1/tracks/7KqjPr2vj8CwQ1cV2swc57",
        "id": "7KqjPr2vj8CwQ1cV2swc57",
        "is_local": false,
        "name": "Shut Up And Dance",
        "popularity": 42,
        "preview_url": null,
        "track_number": 8,
        "type": "track",
        "uri": "spotify:track:7KqjPr2vj8CwQ1cV2swc57"
      },
      {
        "album": {
          "album_type": "single",
          "artists": [
            {
              "external_urls": {
                "spotify":
                  "https://open.spotify.com/artist/5dStRnsw0zCLVtMOe6X1d0"
              },
              "href":
                "https://api.spotify.com/v1/artists/5dStRnsw0zCLVtMOe6X1d0",
              "id": "5dStRnsw0zCLVtMOe6X1d0",
              "name": "Fun Guns",
              "type": "artist",
              "uri": "spotify:artist:5dStRnsw0zCLVtMOe6X1d0"
            }
          ],
          "available_markets": [
            "AD",
            "AR",
            "AT",
            "AU",
            "BE",
            "BG",
            "BO",
            "BR",
            "CA",
            "CH",
            "CL",
            "CO",
            "CR",
            "CY",
            "CZ",
            "DE",
            "DK",
            "DO",
            "EC",
            "EE",
            "ES",
            "FI",
            "FR",
            "GB",
            "GR",
            "GT",
            "HK",
            "HN",
            "HU",
            "ID",
            "IE",
            "IL",
            "IS",
            "IT",
            "JP",
            "LI",
            "LT",
            "LU",
            "LV",
            "MC",
            "MT",
            "MX",
            "MY",
            "NI",
            "NL",
            "NO",
            "NZ",
            "PA",
            "PE",
            "PH",
            "PL",
            "PT",
            "PY",
            "RO",
            "SE",
            "SG",
            "SK",
            "SV",
            "TH",
            "TR",
            "TW",
            "US",
            "UY",
            "VN",
            "ZA"
          ],
          "external_urls": {
            "spotify": "https://open.spotify.com/album/02IFa1yTVz83AvE0WP7Zce"
          },
          "href": "https://api.spotify.com/v1/albums/02IFa1yTVz83AvE0WP7Zce",
          "id": "02IFa1yTVz83AvE0WP7Zce",
          "images": [
            {
              "height": 640,
              "url":
                "https://i.scdn.co/image/f4fd30e2750de3d5e38cfd98285f896f5f207630",
              "width": 640
            },
            {
              "height": 300,
              "url":
                "https://i.scdn.co/image/e667e7c7133a4dbe73e866427d70738dab0d8017",
              "width": 300
            },
            {
              "height": 64,
              "url":
                "https://i.scdn.co/image/f2f9e2f981aae53f9bf9b7a5b9c023358f1b491f",
              "width": 64
            }
          ],
          "name": "Get Up And Move",
          "release_date": "2015-03-12",
          "release_date_precision": "day",
          "type": "album",
          "uri": "spotify:album:02IFa1yTVz83AvE0WP7Zce"
        },
        "artists": [
          {
            "external_urls": {
              "spotify":
                "https://open.spotify.com/artist/5dStRnsw0zCLVtMOe6X1d0"
            },
            "href": "https://api.spotify.com/v1/artists/5dStRnsw0zCLVtMOe6X1d0",
            "id": "5dStRnsw0zCLVtMOe6X1d0",
            "name": "Fun Guns",
            "type": "artist",
            "uri": "spotify:artist:5dStRnsw0zCLVtMOe6X1d0"
          }
        ],
        "available_markets": [
          "AD",
          "AR",
          "AT",
          "AU",
          "BE",
          "BG",
          "BO",
          "BR",
          "CA",
          "CH",
          "CL",
          "CO",
          "CR",
          "CY",
          "CZ",
          "DE",
          "DK",
          "DO",
          "EC",
          "EE",
          "ES",
          "FI",
          "FR",
          "GB",
          "GR",
          "GT",
          "HK",
          "HN",
          "HU",
          "ID",
          "IE",
          "IL",
          "IS",
          "IT",
          "JP",
          "LI",
          "LT",
          "LU",
          "LV",
          "MC",
          "MT",
          "MX",
          "MY",
          "NI",
          "NL",
          "NO",
          "NZ",
          "PA",
          "PE",
          "PH",
          "PL",
          "PT",
          "PY",
          "RO",
          "SE",
          "SG",
          "SK",
          "SV",
          "TH",
          "TR",
          "TW",
          "US",
          "UY",
          "VN",
          "ZA"
        ],
        "disc_number": 1,
        "duration_ms": 204159,
        "explicit": false,
        "external_ids": { "isrc": "USQY51541183" },
        "external_urls": {
          "spotify": "https://open.spotify.com/track/4KYAV74fzH1rUipmxXejw1"
        },
        "href": "https://api.spotify.com/v1/tracks/4KYAV74fzH1rUipmxXejw1",
        "id": "4KYAV74fzH1rUipmxXejw1",
        "is_local": false,
        "name": "Shut Up And Dance With Me",
        "popularity": 48,
        "preview_url":
          "https://p.scdn.co/mp3-preview/7c51ac79bd31db8df059470568311a19685e65d4?cid=cd2cbf7b258249d1b36e316ca7fee072",
        "track_number": 3,
        "type": "track",
        "uri": "spotify:track:4KYAV74fzH1rUipmxXejw1"
      },
      {
        "album": {
          "album_type": "album",
          "artists": [
            {
              "external_urls": {
                "spotify":
                  "https://open.spotify.com/artist/5BKzvAPtNXnt0LwzGvKOH3"
              },
              "href":
                "https://api.spotify.com/v1/artists/5BKzvAPtNXnt0LwzGvKOH3",
              "id": "5BKzvAPtNXnt0LwzGvKOH3",
              "name": "Aaron Watson",
              "type": "artist",
              "uri": "spotify:artist:5BKzvAPtNXnt0LwzGvKOH3"
            }
          ],
          "available_markets": ["CA", "US"],
          "external_urls": {
            "spotify": "https://open.spotify.com/album/0JLxbOIxLJ5oDqYLOxJlnM"
          },
          "href": "https://api.spotify.com/v1/albums/0JLxbOIxLJ5oDqYLOxJlnM",
          "id": "0JLxbOIxLJ5oDqYLOxJlnM",
          "images": [
            {
              "height": 640,
              "url":
                "https://i.scdn.co/image/8fe4b2d28e543128ccc13a7a2327f4f445963972",
              "width": 640
            },
            {
              "height": 300,
              "url":
                "https://i.scdn.co/image/330799dec4e7347e2d651a60cdbc8ac41c219d4c",
              "width": 300
            },
            {
              "height": 64,
              "url":
                "https://i.scdn.co/image/b8585a90df8e4067331a69cea7a775525f35795d",
              "width": 64
            }
          ],
          "name": "Shut up and Dance",
          "release_date": "2002",
          "release_date_precision": "year",
          "type": "album",
          "uri": "spotify:album:0JLxbOIxLJ5oDqYLOxJlnM"
        },
        "artists": [
          {
            "external_urls": {
              "spotify":
                "https://open.spotify.com/artist/5BKzvAPtNXnt0LwzGvKOH3"
            },
            "href": "https://api.spotify.com/v1/artists/5BKzvAPtNXnt0LwzGvKOH3",
            "id": "5BKzvAPtNXnt0LwzGvKOH3",
            "name": "Aaron Watson",
            "type": "artist",
            "uri": "spotify:artist:5BKzvAPtNXnt0LwzGvKOH3"
          }
        ],
        "available_markets": ["CA", "US"],
        "disc_number": 1,
        "duration_ms": 219773,
        "explicit": false,
        "external_ids": { "isrc": "US4AB0400013" },
        "external_urls": {
          "spotify": "https://open.spotify.com/track/3HzSOjDR9PBB2L5mx3i1Pq"
        },
        "href": "https://api.spotify.com/v1/tracks/3HzSOjDR9PBB2L5mx3i1Pq",
        "id": "3HzSOjDR9PBB2L5mx3i1Pq",
        "is_local": false,
        "name": "Off the Record",
        "popularity": 42,
        "preview_url":
          "https://p.scdn.co/mp3-preview/8bf25f0c953a6e59863fce74b8ec01b68ba15b7b?cid=cd2cbf7b258249d1b36e316ca7fee072",
        "track_number": 13,
        "type": "track",
        "uri": "spotify:track:3HzSOjDR9PBB2L5mx3i1Pq"
      },
      {
        "album": {
          "album_type": "single",
          "artists": [
            {
              "external_urls": {
                "spotify":
                  "https://open.spotify.com/artist/1KYszkVzlhV3rAqmAcYIgd"
              },
              "href":
                "https://api.spotify.com/v1/artists/1KYszkVzlhV3rAqmAcYIgd",
              "id": "1KYszkVzlhV3rAqmAcYIgd",
              "name": "Victorious Cast",
              "type": "artist",
              "uri": "spotify:artist:1KYszkVzlhV3rAqmAcYIgd"
            }
          ],
          "available_markets": ["AU", "CA", "NZ", "US"],
          "external_urls": {
            "spotify": "https://open.spotify.com/album/5wfCTE4O3jyFQPmfSpaWz0"
          },
          "href": "https://api.spotify.com/v1/albums/5wfCTE4O3jyFQPmfSpaWz0",
          "id": "5wfCTE4O3jyFQPmfSpaWz0",
          "images": [
            {
              "height": 635,
              "url":
                "https://i.scdn.co/image/3d4c396d089a67c842d3b762e0fbab8e014e83d2",
              "width": 640
            },
            {
              "height": 298,
              "url":
                "https://i.scdn.co/image/15b6a2664d4c796fb08afcd04da7b40e44e247f6",
              "width": 300
            },
            {
              "height": 64,
              "url":
                "https://i.scdn.co/image/27948c7adf8aed437265dda9975033e11f9e5751",
              "width": 64
            }
          ],
          "name": "Victorious 2.0: More Music From The Hit TV Show",
          "release_date": "2012-06-05",
          "release_date_precision": "day",
          "type": "album",
          "uri": "spotify:album:5wfCTE4O3jyFQPmfSpaWz0"
        },
        "artists": [
          {
            "external_urls": {
              "spotify":
                "https://open.spotify.com/artist/1KYszkVzlhV3rAqmAcYIgd"
            },
            "href": "https://api.spotify.com/v1/artists/1KYszkVzlhV3rAqmAcYIgd",
            "id": "1KYszkVzlhV3rAqmAcYIgd",
            "name": "Victorious Cast",
            "type": "artist",
            "uri": "spotify:artist:1KYszkVzlhV3rAqmAcYIgd"
          },
          {
            "external_urls": {
              "spotify":
                "https://open.spotify.com/artist/2OTfr6S2kuHRYStjt1IkY6"
            },
            "href": "https://api.spotify.com/v1/artists/2OTfr6S2kuHRYStjt1IkY6",
            "id": "2OTfr6S2kuHRYStjt1IkY6",
            "name": "Victoria Justice",
            "type": "artist",
            "uri": "spotify:artist:2OTfr6S2kuHRYStjt1IkY6"
          }
        ],
        "available_markets": ["AU", "CA", "NZ", "US"],
        "disc_number": 1,
        "duration_ms": 177120,
        "explicit": false,
        "external_ids": { "isrc": "USSM11202272" },
        "external_urls": {
          "spotify": "https://open.spotify.com/track/3myg6Gpulo6fD0EOnz5dOQ"
        },
        "href": "https://api.spotify.com/v1/tracks/3myg6Gpulo6fD0EOnz5dOQ",
        "id": "3myg6Gpulo6fD0EOnz5dOQ",
        "is_local": false,
        "name": "Shut Up And Dance",
        "popularity": 41,
        "preview_url":
          "https://p.scdn.co/mp3-preview/23e95eaca70bea7364473a4051d00ee371475416?cid=cd2cbf7b258249d1b36e316ca7fee072",
        "track_number": 3,
        "type": "track",
        "uri": "spotify:track:3myg6Gpulo6fD0EOnz5dOQ"
      },
      {
        "album": {
          "album_type": "album",
          "artists": [
            {
              "external_urls": {
                "spotify":
                  "https://open.spotify.com/artist/7h4j9YTJJuAHzLCc3KCvYu"
              },
              "href":
                "https://api.spotify.com/v1/artists/7h4j9YTJJuAHzLCc3KCvYu",
              "id": "7h4j9YTJJuAHzLCc3KCvYu",
              "name": "Kina Grannis",
              "type": "artist",
              "uri": "spotify:artist:7h4j9YTJJuAHzLCc3KCvYu"
            }
          ],
          "available_markets": [
            "AD",
            "AR",
            "AT",
            "AU",
            "BE",
            "BG",
            "BO",
            "BR",
            "CA",
            "CH",
            "CL",
            "CO",
            "CR",
            "CY",
            "CZ",
            "DE",
            "DK",
            "DO",
            "EC",
            "EE",
            "ES",
            "FI",
            "FR",
            "GB",
            "GR",
            "GT",
            "HK",
            "HN",
            "HU",
            "ID",
            "IE",
            "IL",
            "IS",
            "IT",
            "JP",
            "LI",
            "LT",
            "LU",
            "LV",
            "MC",
            "MT",
            "MX",
            "MY",
            "NI",
            "NL",
            "NO",
            "NZ",
            "PA",
            "PE",
            "PH",
            "PL",
            "PT",
            "PY",
            "RO",
            "SE",
            "SG",
            "SK",
            "SV",
            "TH",
            "TR",
            "TW",
            "US",
            "UY",
            "VN",
            "ZA"
          ],
          "external_urls": {
            "spotify": "https://open.spotify.com/album/4IYny9vZHGoL7TUcl3TEWp"
          },
          "href": "https://api.spotify.com/v1/albums/4IYny9vZHGoL7TUcl3TEWp",
          "id": "4IYny9vZHGoL7TUcl3TEWp",
          "images": [
            {
              "height": 640,
              "url":
                "https://i.scdn.co/image/b9b74b1a916b7ee796b1bb93bb4767096887ec7a",
              "width": 640
            },
            {
              "height": 300,
              "url":
                "https://i.scdn.co/image/a3c0304c97b748beb12baa4e5f1bd322768ab658",
              "width": 300
            },
            {
              "height": 64,
              "url":
                "https://i.scdn.co/image/2a823aed2ae7d91e90111c54ad3e2838e2c407f7",
              "width": 64
            }
          ],
          "name": "The Living Room Sessions Vol. 3",
          "release_date": "2017-01-13",
          "release_date_precision": "day",
          "type": "album",
          "uri": "spotify:album:4IYny9vZHGoL7TUcl3TEWp"
        },
        "artists": [
          {
            "external_urls": {
              "spotify":
                "https://open.spotify.com/artist/7h4j9YTJJuAHzLCc3KCvYu"
            },
            "href": "https://api.spotify.com/v1/artists/7h4j9YTJJuAHzLCc3KCvYu",
            "id": "7h4j9YTJJuAHzLCc3KCvYu",
            "name": "Kina Grannis",
            "type": "artist",
            "uri": "spotify:artist:7h4j9YTJJuAHzLCc3KCvYu"
          }
        ],
        "available_markets": [
          "AD",
          "AR",
          "AT",
          "AU",
          "BE",
          "BG",
          "BO",
          "BR",
          "CA",
          "CH",
          "CL",
          "CO",
          "CR",
          "CY",
          "CZ",
          "DE",
          "DK",
          "DO",
          "EC",
          "EE",
          "ES",
          "FI",
          "FR",
          "GB",
          "GR",
          "GT",
          "HK",
          "HN",
          "HU",
          "ID",
          "IE",
          "IL",
          "IS",
          "IT",
          "JP",
          "LI",
          "LT",
          "LU",
          "LV",
          "MC",
          "MT",
          "MX",
          "MY",
          "NI",
          "NL",
          "NO",
          "NZ",
          "PA",
          "PE",
          "PH",
          "PL",
          "PT",
          "PY",
          "RO",
          "SE",
          "SG",
          "SK",
          "SV",
          "TH",
          "TR",
          "TW",
          "US",
          "UY",
          "VN",
          "ZA"
        ],
        "disc_number": 1,
        "duration_ms": 159009,
        "explicit": false,
        "external_ids": { "isrc": "GBDMT1600291" },
        "external_urls": {
          "spotify": "https://open.spotify.com/track/7znZOKabUQzUMXjgMXDuem"
        },
        "href": "https://api.spotify.com/v1/tracks/7znZOKabUQzUMXjgMXDuem",
        "id": "7znZOKabUQzUMXjgMXDuem",
        "is_local": false,
        "name": "Shut Up and Dance",
        "popularity": 48,
        "preview_url":
          "https://p.scdn.co/mp3-preview/8891ea6303d7566bfc1d9dc4cf3db730594a8b74?cid=cd2cbf7b258249d1b36e316ca7fee072",
        "track_number": 2,
        "type": "track",
        "uri": "spotify:track:7znZOKabUQzUMXjgMXDuem"
      },
      {
        "album": {
          "album_type": "single",
          "artists": [
            {
              "external_urls": {
                "spotify":
                  "https://open.spotify.com/artist/6dC0rIJNLSFZwqckLgXJ8p"
              },
              "href":
                "https://api.spotify.com/v1/artists/6dC0rIJNLSFZwqckLgXJ8p",
              "id": "6dC0rIJNLSFZwqckLgXJ8p",
              "name": "Timeflies",
              "type": "artist",
              "uri": "spotify:artist:6dC0rIJNLSFZwqckLgXJ8p"
            }
          ],
          "available_markets": [
            "AD",
            "AR",
            "AT",
            "AU",
            "BE",
            "BG",
            "BO",
            "BR",
            "CA",
            "CH",
            "CL",
            "CO",
            "CR",
            "CY",
            "CZ",
            "DE",
            "DK",
            "DO",
            "EC",
            "EE",
            "ES",
            "FI",
            "FR",
            "GB",
            "GR",
            "GT",
            "HK",
            "HN",
            "HU",
            "ID",
            "IE",
            "IL",
            "IS",
            "IT",
            "JP",
            "LI",
            "LT",
            "LU",
            "LV",
            "MC",
            "MT",
            "MX",
            "MY",
            "NI",
            "NL",
            "NO",
            "NZ",
            "PA",
            "PE",
            "PH",
            "PL",
            "PT",
            "PY",
            "RO",
            "SE",
            "SG",
            "SK",
            "SV",
            "TH",
            "TR",
            "TW",
            "US",
            "UY",
            "VN",
            "ZA"
          ],
          "external_urls": {
            "spotify": "https://open.spotify.com/album/5DYTR3Z4vwjg7IrKUIJ1xz"
          },
          "href": "https://api.spotify.com/v1/albums/5DYTR3Z4vwjg7IrKUIJ1xz",
          "id": "5DYTR3Z4vwjg7IrKUIJ1xz",
          "images": [
            {
              "height": 640,
              "url":
                "https://i.scdn.co/image/5d479c4b6363dedbdd8059d8d91edc0f77430b7a",
              "width": 640
            },
            {
              "height": 300,
              "url":
                "https://i.scdn.co/image/a9af1c1c96ca56f2423f4ebdab2943d9cae61dd7",
              "width": 300
            },
            {
              "height": 64,
              "url":
                "https://i.scdn.co/image/1bc5c81166c3d61c7938bd0a028b693fc2a2e97f",
              "width": 64
            }
          ],
          "name": "Timeflies Tuesday, Vol. 2",
          "release_date": "2017-07-14",
          "release_date_precision": "day",
          "type": "album",
          "uri": "spotify:album:5DYTR3Z4vwjg7IrKUIJ1xz"
        },
        "artists": [
          {
            "external_urls": {
              "spotify":
                "https://open.spotify.com/artist/6dC0rIJNLSFZwqckLgXJ8p"
            },
            "href": "https://api.spotify.com/v1/artists/6dC0rIJNLSFZwqckLgXJ8p",
            "id": "6dC0rIJNLSFZwqckLgXJ8p",
            "name": "Timeflies",
            "type": "artist",
            "uri": "spotify:artist:6dC0rIJNLSFZwqckLgXJ8p"
          }
        ],
        "available_markets": [
          "AD",
          "AR",
          "AT",
          "AU",
          "BE",
          "BG",
          "BO",
          "BR",
          "CA",
          "CH",
          "CL",
          "CO",
          "CR",
          "CY",
          "CZ",
          "DE",
          "DK",
          "DO",
          "EC",
          "EE",
          "ES",
          "FI",
          "FR",
          "GB",
          "GR",
          "GT",
          "HK",
          "HN",
          "HU",
          "ID",
          "IE",
          "IL",
          "IS",
          "IT",
          "JP",
          "LI",
          "LT",
          "LU",
          "LV",
          "MC",
          "MT",
          "MX",
          "MY",
          "NI",
          "NL",
          "NO",
          "NZ",
          "PA",
          "PE",
          "PH",
          "PL",
          "PT",
          "PY",
          "RO",
          "SE",
          "SG",
          "SK",
          "SV",
          "TH",
          "TR",
          "TW",
          "US",
          "UY",
          "VN",
          "ZA"
        ],
        "disc_number": 1,
        "duration_ms": 181132,
        "explicit": true,
        "external_ids": { "isrc": "TCADD1787352" },
        "external_urls": {
          "spotify": "https://open.spotify.com/track/2CJmBGLT6kHBzCRbxQC7br"
        },
        "href": "https://api.spotify.com/v1/tracks/2CJmBGLT6kHBzCRbxQC7br",
        "id": "2CJmBGLT6kHBzCRbxQC7br",
        "is_local": false,
        "name": "Shut up and Dance",
        "popularity": 39,
        "preview_url":
          "https://p.scdn.co/mp3-preview/8630b8db3f0a3cda262c4d6ce65c5e82a5505494?cid=cd2cbf7b258249d1b36e316ca7fee072",
        "track_number": 3,
        "type": "track",
        "uri": "spotify:track:2CJmBGLT6kHBzCRbxQC7br"
      },
      {
        "album": {
          "album_type": "album",
          "artists": [
            {
              "external_urls": {
                "spotify":
                  "https://open.spotify.com/artist/5BKzvAPtNXnt0LwzGvKOH3"
              },
              "href":
                "https://api.spotify.com/v1/artists/5BKzvAPtNXnt0LwzGvKOH3",
              "id": "5BKzvAPtNXnt0LwzGvKOH3",
              "name": "Aaron Watson",
              "type": "artist",
              "uri": "spotify:artist:5BKzvAPtNXnt0LwzGvKOH3"
            }
          ],
          "available_markets": ["CA", "US"],
          "external_urls": {
            "spotify": "https://open.spotify.com/album/0JLxbOIxLJ5oDqYLOxJlnM"
          },
          "href": "https://api.spotify.com/v1/albums/0JLxbOIxLJ5oDqYLOxJlnM",
          "id": "0JLxbOIxLJ5oDqYLOxJlnM",
          "images": [
            {
              "height": 640,
              "url":
                "https://i.scdn.co/image/8fe4b2d28e543128ccc13a7a2327f4f445963972",
              "width": 640
            },
            {
              "height": 300,
              "url":
                "https://i.scdn.co/image/330799dec4e7347e2d651a60cdbc8ac41c219d4c",
              "width": 300
            },
            {
              "height": 64,
              "url":
                "https://i.scdn.co/image/b8585a90df8e4067331a69cea7a775525f35795d",
              "width": 64
            }
          ],
          "name": "Shut up and Dance",
          "release_date": "2002",
          "release_date_precision": "year",
          "type": "album",
          "uri": "spotify:album:0JLxbOIxLJ5oDqYLOxJlnM"
        },
        "artists": [
          {
            "external_urls": {
              "spotify":
                "https://open.spotify.com/artist/5BKzvAPtNXnt0LwzGvKOH3"
            },
            "href": "https://api.spotify.com/v1/artists/5BKzvAPtNXnt0LwzGvKOH3",
            "id": "5BKzvAPtNXnt0LwzGvKOH3",
            "name": "Aaron Watson",
            "type": "artist",
            "uri": "spotify:artist:5BKzvAPtNXnt0LwzGvKOH3"
          }
        ],
        "available_markets": ["CA", "US"],
        "disc_number": 1,
        "duration_ms": 334693,
        "explicit": false,
        "external_ids": { "isrc": "US4AB0400009" },
        "external_urls": {
          "spotify": "https://open.spotify.com/track/4YMJcsiZlRFNTdlgQWYk2h"
        },
        "href": "https://api.spotify.com/v1/tracks/4YMJcsiZlRFNTdlgQWYk2h",
        "id": "4YMJcsiZlRFNTdlgQWYk2h",
        "is_local": false,
        "name": "Lonely Lubbock Lights",
        "popularity": 38,
        "preview_url":
          "https://p.scdn.co/mp3-preview/6c7e6445711f19cb288cfd3b2529bb0f081b8f76?cid=cd2cbf7b258249d1b36e316ca7fee072",
        "track_number": 9,
        "type": "track",
        "uri": "spotify:track:4YMJcsiZlRFNTdlgQWYk2h"
      },
      {
        "album": {
          "album_type": "album",
          "artists": [
            {
              "external_urls": {
                "spotify":
                  "https://open.spotify.com/artist/1yQ8S4xdGOGbUcpaPR6hCM"
              },
              "href":
                "https://api.spotify.com/v1/artists/1yQ8S4xdGOGbUcpaPR6hCM",
              "id": "1yQ8S4xdGOGbUcpaPR6hCM",
              "name": "Straight No Chaser",
              "type": "artist",
              "uri": "spotify:artist:1yQ8S4xdGOGbUcpaPR6hCM"
            }
          ],
          "available_markets": [
            "AD",
            "AR",
            "AT",
            "AU",
            "BE",
            "BG",
            "BO",
            "BR",
            "CA",
            "CH",
            "CL",
            "CO",
            "CR",
            "CY",
            "CZ",
            "DE",
            "DK",
            "DO",
            "EC",
            "EE",
            "ES",
            "FI",
            "FR",
            "GB",
            "GR",
            "GT",
            "HK",
            "HN",
            "HU",
            "ID",
            "IE",
            "IL",
            "IS",
            "IT",
            "JP",
            "LI",
            "LT",
            "LU",
            "LV",
            "MC",
            "MT",
            "MX",
            "MY",
            "NI",
            "NL",
            "NO",
            "NZ",
            "PA",
            "PE",
            "PH",
            "PL",
            "PT",
            "PY",
            "RO",
            "SE",
            "SG",
            "SK",
            "SV",
            "TH",
            "TR",
            "TW",
            "US",
            "UY",
            "VN",
            "ZA"
          ],
          "external_urls": {
            "spotify": "https://open.spotify.com/album/4WqVsi6JHlj6w2cBbE8nS7"
          },
          "href": "https://api.spotify.com/v1/albums/4WqVsi6JHlj6w2cBbE8nS7",
          "id": "4WqVsi6JHlj6w2cBbE8nS7",
          "images": [
            {
              "height": 640,
              "url":
                "https://i.scdn.co/image/ae74acc0a6e22a9526e04632b2609507909e7d74",
              "width": 640
            },
            {
              "height": 300,
              "url":
                "https://i.scdn.co/image/fe963c3ffd242aeb437c93afa97399e295c569fa",
              "width": 300
            },
            {
              "height": 64,
              "url":
                "https://i.scdn.co/image/86fc3f12d6a5c32e5365e9c1530ceb3075fff606",
              "width": 64
            }
          ],
          "name": "The New Old Fashioned (Deluxe)",
          "release_date": "2015-10-30",
          "release_date_precision": "day",
          "type": "album",
          "uri": "spotify:album:4WqVsi6JHlj6w2cBbE8nS7"
        },
        "artists": [
          {
            "external_urls": {
              "spotify":
                "https://open.spotify.com/artist/1yQ8S4xdGOGbUcpaPR6hCM"
            },
            "href": "https://api.spotify.com/v1/artists/1yQ8S4xdGOGbUcpaPR6hCM",
            "id": "1yQ8S4xdGOGbUcpaPR6hCM",
            "name": "Straight No Chaser",
            "type": "artist",
            "uri": "spotify:artist:1yQ8S4xdGOGbUcpaPR6hCM"
          }
        ],
        "available_markets": [
          "AD",
          "AR",
          "AT",
          "AU",
          "BE",
          "BG",
          "BO",
          "BR",
          "CA",
          "CH",
          "CL",
          "CO",
          "CR",
          "CY",
          "CZ",
          "DE",
          "DK",
          "DO",
          "EC",
          "EE",
          "ES",
          "FI",
          "FR",
          "GB",
          "GR",
          "GT",
          "HK",
          "HN",
          "HU",
          "ID",
          "IE",
          "IL",
          "IS",
          "IT",
          "JP",
          "LI",
          "LT",
          "LU",
          "LV",
          "MC",
          "MT",
          "MX",
          "MY",
          "NI",
          "NL",
          "NO",
          "NZ",
          "PA",
          "PE",
          "PH",
          "PL",
          "PT",
          "PY",
          "RO",
          "SE",
          "SG",
          "SK",
          "SV",
          "TH",
          "TR",
          "TW",
          "US",
          "UY",
          "VN",
          "ZA"
        ],
        "disc_number": 1,
        "duration_ms": 167933,
        "explicit": false,
        "external_ids": { "isrc": "USAT21503334" },
        "external_urls": {
          "spotify": "https://open.spotify.com/track/4Q4G6wehDTKF8iHFC7L5pT"
        },
        "href": "https://api.spotify.com/v1/tracks/4Q4G6wehDTKF8iHFC7L5pT",
        "id": "4Q4G6wehDTKF8iHFC7L5pT",
        "is_local": false,
        "name": "Shut Up And Dance",
        "popularity": 37,
        "preview_url":
          "https://p.scdn.co/mp3-preview/dc6fdc340eae47f7b6077b9175665f1aaa21975d?cid=cd2cbf7b258249d1b36e316ca7fee072",
        "track_number": 11,
        "type": "track",
        "uri": "spotify:track:4Q4G6wehDTKF8iHFC7L5pT"
      },
      {
        "album": {
          "album_type": "album",
          "artists": [
            {
              "external_urls": {
                "spotify":
                  "https://open.spotify.com/artist/4ZZVk8undJqXJqQ1GHCTp2"
              },
              "href":
                "https://api.spotify.com/v1/artists/4ZZVk8undJqXJqQ1GHCTp2",
              "id": "4ZZVk8undJqXJqQ1GHCTp2",
              "name": "Simply Three",
              "type": "artist",
              "uri": "spotify:artist:4ZZVk8undJqXJqQ1GHCTp2"
            }
          ],
          "available_markets": [
            "AD",
            "AR",
            "AT",
            "AU",
            "BE",
            "BG",
            "BO",
            "BR",
            "CA",
            "CH",
            "CL",
            "CO",
            "CR",
            "CY",
            "CZ",
            "DE",
            "DK",
            "DO",
            "EC",
            "EE",
            "ES",
            "FI",
            "FR",
            "GB",
            "GR",
            "GT",
            "HK",
            "HN",
            "HU",
            "ID",
            "IE",
            "IL",
            "IS",
            "IT",
            "JP",
            "LI",
            "LT",
            "LU",
            "LV",
            "MC",
            "MT",
            "MX",
            "MY",
            "NI",
            "NL",
            "NO",
            "NZ",
            "PA",
            "PE",
            "PH",
            "PL",
            "PT",
            "PY",
            "RO",
            "SE",
            "SG",
            "SK",
            "SV",
            "TH",
            "TR",
            "TW",
            "US",
            "UY",
            "VN",
            "ZA"
          ],
          "external_urls": {
            "spotify": "https://open.spotify.com/album/197DQ5RKZsUWS8IQUnamQL"
          },
          "href": "https://api.spotify.com/v1/albums/197DQ5RKZsUWS8IQUnamQL",
          "id": "197DQ5RKZsUWS8IQUnamQL",
          "images": [
            {
              "height": 640,
              "url":
                "https://i.scdn.co/image/18b6ec614ab6cf0207a17866d7c8356d2793ece7",
              "width": 640
            },
            {
              "height": 300,
              "url":
                "https://i.scdn.co/image/d7d8a536e6d69e10e4325a03f76858488b75d6e5",
              "width": 300
            },
            {
              "height": 64,
              "url":
                "https://i.scdn.co/image/3fc4806c7d01d504f448ee444d1040511de8e1be",
              "width": 64
            }
          ],
          "name": "Volume 3",
          "release_date": "2016-03-01",
          "release_date_precision": "day",
          "type": "album",
          "uri": "spotify:album:197DQ5RKZsUWS8IQUnamQL"
        },
        "artists": [
          {
            "external_urls": {
              "spotify":
                "https://open.spotify.com/artist/4ZZVk8undJqXJqQ1GHCTp2"
            },
            "href": "https://api.spotify.com/v1/artists/4ZZVk8undJqXJqQ1GHCTp2",
            "id": "4ZZVk8undJqXJqQ1GHCTp2",
            "name": "Simply Three",
            "type": "artist",
            "uri": "spotify:artist:4ZZVk8undJqXJqQ1GHCTp2"
          }
        ],
        "available_markets": [
          "AD",
          "AR",
          "AT",
          "AU",
          "BE",
          "BG",
          "BO",
          "BR",
          "CA",
          "CH",
          "CL",
          "CO",
          "CR",
          "CY",
          "CZ",
          "DE",
          "DK",
          "DO",
          "EC",
          "EE",
          "ES",
          "FI",
          "FR",
          "GB",
          "GR",
          "GT",
          "HK",
          "HN",
          "HU",
          "ID",
          "IE",
          "IL",
          "IS",
          "IT",
          "JP",
          "LI",
          "LT",
          "LU",
          "LV",
          "MC",
          "MT",
          "MX",
          "MY",
          "NI",
          "NL",
          "NO",
          "NZ",
          "PA",
          "PE",
          "PH",
          "PL",
          "PT",
          "PY",
          "RO",
          "SE",
          "SG",
          "SK",
          "SV",
          "TH",
          "TR",
          "TW",
          "US",
          "UY",
          "VN",
          "ZA"
        ],
        "disc_number": 1,
        "duration_ms": 200586,
        "explicit": false,
        "external_ids": { "isrc": "QM56S1650014" },
        "external_urls": {
          "spotify": "https://open.spotify.com/track/6SN2zUpien60ooLq2hmVB2"
        },
        "href": "https://api.spotify.com/v1/tracks/6SN2zUpien60ooLq2hmVB2",
        "id": "6SN2zUpien60ooLq2hmVB2",
        "is_local": false,
        "name": "Shut up and Dance",
        "popularity": 41,
        "preview_url":
          "https://p.scdn.co/mp3-preview/b4e9b77bbbf165a1648d8369b7c7e8f34cdc9142?cid=cd2cbf7b258249d1b36e316ca7fee072",
        "track_number": 4,
        "type": "track",
        "uri": "spotify:track:6SN2zUpien60ooLq2hmVB2"
      },
      {
        "album": {
          "album_type": "single",
          "artists": [
            {
              "external_urls": {
                "spotify":
                  "https://open.spotify.com/artist/2rG8OO6ysixVvfdTD1JfMr"
              },
              "href":
                "https://api.spotify.com/v1/artists/2rG8OO6ysixVvfdTD1JfMr",
              "id": "2rG8OO6ysixVvfdTD1JfMr",
              "name": "Max Pizzolante",
              "type": "artist",
              "uri": "spotify:artist:2rG8OO6ysixVvfdTD1JfMr"
            }
          ],
          "available_markets": [
            "AD",
            "AR",
            "AT",
            "AU",
            "BE",
            "BG",
            "BO",
            "BR",
            "CA",
            "CH",
            "CL",
            "CO",
            "CR",
            "CY",
            "CZ",
            "DE",
            "DK",
            "DO",
            "EC",
            "EE",
            "ES",
            "FI",
            "FR",
            "GB",
            "GR",
            "GT",
            "HK",
            "HN",
            "HU",
            "ID",
            "IE",
            "IL",
            "IS",
            "IT",
            "JP",
            "LI",
            "LT",
            "LU",
            "LV",
            "MC",
            "MT",
            "MX",
            "MY",
            "NI",
            "NL",
            "NO",
            "NZ",
            "PA",
            "PE",
            "PH",
            "PL",
            "PT",
            "PY",
            "RO",
            "SE",
            "SG",
            "SK",
            "SV",
            "TH",
            "TR",
            "TW",
            "US",
            "UY",
            "VN",
            "ZA"
          ],
          "external_urls": {
            "spotify": "https://open.spotify.com/album/1T9EbQoitPBc9N0qoBsZlK"
          },
          "href": "https://api.spotify.com/v1/albums/1T9EbQoitPBc9N0qoBsZlK",
          "id": "1T9EbQoitPBc9N0qoBsZlK",
          "images": [
            {
              "height": 640,
              "url":
                "https://i.scdn.co/image/c47566218a0fba4b542f44b902253327448ea57b",
              "width": 640
            },
            {
              "height": 300,
              "url":
                "https://i.scdn.co/image/a68a9bd5994c41f04c1850c2f2d763d84ee7428b",
              "width": 300
            },
            {
              "height": 64,
              "url":
                "https://i.scdn.co/image/3a556889d4bdaa308ce1cbe13b65e8554564ff70",
              "width": 64
            }
          ],
          "name": "Shut up and Dance (feat. Beto Perez)",
          "release_date": "2016-04-01",
          "release_date_precision": "day",
          "type": "album",
          "uri": "spotify:album:1T9EbQoitPBc9N0qoBsZlK"
        },
        "artists": [
          {
            "external_urls": {
              "spotify":
                "https://open.spotify.com/artist/2rG8OO6ysixVvfdTD1JfMr"
            },
            "href": "https://api.spotify.com/v1/artists/2rG8OO6ysixVvfdTD1JfMr",
            "id": "2rG8OO6ysixVvfdTD1JfMr",
            "name": "MaxPizzolante",
            "type": "artist",
            "uri": "spotify:artist:2rG8OO6ysixVvfdTD1JfMr"
          },
          {
            "external_urls": {
              "spotify":
                "https://open.spotify.com/artist/5xUarxpnDQkuXJbhe6RD3p"
            },
            "href": "https://api.spotify.com/v1/artists/5xUarxpnDQkuXJbhe6RD3p",
            "id": "5xUarxpnDQkuXJbhe6RD3p",
            "name": "Beto Perez",
            "type": "artist",
            "uri": "spotify:artist:5xUarxpnDQkuXJbhe6RD3p"
          }
        ],
        "available_markets": [
          "AD",
          "AR",
          "AT",
          "AU",
          "BE",
          "BG",
          "BO",
          "BR",
          "CA",
          "CH",
          "CL",
          "CO",
          "CR",
          "CY",
          "CZ",
          "DE",
          "DK",
          "DO",
          "EC",
          "EE",
          "ES",
          "FI",
          "FR",
          "GB",
          "GR",
          "GT",
          "HK",
          "HN",
          "HU",
          "ID",
          "IE",
          "IL",
          "IS",
          "IT",
          "JP",
          "LI",
          "LT",
          "LU",
          "LV",
          "MC",
          "MT",
          "MX",
          "MY",
          "NI",
          "NL",
          "NO",
          "NZ",
          "PA",
          "PE",
          "PH",
          "PL",
          "PT",
          "PY",
          "RO",
          "SE",
          "SG",
          "SK",
          "SV",
          "TH",
          "TR",
          "TW",
          "US",
          "UY",
          "VN",
          "ZA"
        ],
        "disc_number": 1,
        "duration_ms": 239773,
        "explicit": false,
        "external_ids": { "isrc": "TCACM1609478" },
        "external_urls": {
          "spotify": "https://open.spotify.com/track/1HYss85nHC8VhO4ZlXZ32p"
        },
        "href": "https://api.spotify.com/v1/tracks/1HYss85nHC8VhO4ZlXZ32p",
        "id": "1HYss85nHC8VhO4ZlXZ32p",
        "is_local": false,
        "name": "Shut up and Dance (feat. Beto Perez)",
        "popularity": 45,
        "preview_url":
          "https://p.scdn.co/mp3-preview/177b99bba85dc50d91531965c11c797a40645231?cid=cd2cbf7b258249d1b36e316ca7fee072",
        "track_number": 1,
        "type": "track",
        "uri": "spotify:track:1HYss85nHC8VhO4ZlXZ32p"
      },
      {
        "album": {
          "album_type": "album",
          "artists": [
            {
              "external_urls": {
                "spotify":
                  "https://open.spotify.com/artist/5Hc9oDGvStNGmnj44m8sHg"
              },
              "href":
                "https://api.spotify.com/v1/artists/5Hc9oDGvStNGmnj44m8sHg",
              "id": "5Hc9oDGvStNGmnj44m8sHg",
              "name": "Tyler Ward",
              "type": "artist",
              "uri": "spotify:artist:5Hc9oDGvStNGmnj44m8sHg"
            }
          ],
          "available_markets": [
            "AD",
            "AR",
            "AT",
            "AU",
            "BE",
            "BG",
            "BO",
            "BR",
            "CA",
            "CH",
            "CL",
            "CO",
            "CR",
            "CY",
            "CZ",
            "DE",
            "DK",
            "DO",
            "EC",
            "EE",
            "ES",
            "FI",
            "FR",
            "GB",
            "GR",
            "GT",
            "HK",
            "HN",
            "HU",
            "ID",
            "IE",
            "IL",
            "IS",
            "IT",
            "JP",
            "LI",
            "LT",
            "LU",
            "LV",
            "MC",
            "MT",
            "MX",
            "MY",
            "NI",
            "NL",
            "NO",
            "NZ",
            "PA",
            "PE",
            "PH",
            "PL",
            "PT",
            "PY",
            "RO",
            "SE",
            "SG",
            "SK",
            "SV",
            "TH",
            "TR",
            "TW",
            "US",
            "UY",
            "VN",
            "ZA"
          ],
          "external_urls": {
            "spotify": "https://open.spotify.com/album/3SH97wy4KAABVkVBItE8j1"
          },
          "href": "https://api.spotify.com/v1/albums/3SH97wy4KAABVkVBItE8j1",
          "id": "3SH97wy4KAABVkVBItE8j1",
          "images": [
            {
              "height": 640,
              "url":
                "https://i.scdn.co/image/42c715ed628c24b14d9115608efaa491ac3d0091",
              "width": 640
            },
            {
              "height": 300,
              "url":
                "https://i.scdn.co/image/d1d54e23f981ac401f501cec89aee3030b567c6e",
              "width": 300
            },
            {
              "height": 64,
              "url":
                "https://i.scdn.co/image/2bb2b10e16b394fe9e986b7fe06e0fc1e9ac8e4c",
              "width": 64
            }
          ],
          "name": "Cookin' Covers",
          "release_date": "2015-04-13",
          "release_date_precision": "day",
          "type": "album",
          "uri": "spotify:album:3SH97wy4KAABVkVBItE8j1"
        },
        "artists": [
          {
            "external_urls": {
              "spotify":
                "https://open.spotify.com/artist/5Hc9oDGvStNGmnj44m8sHg"
            },
            "href": "https://api.spotify.com/v1/artists/5Hc9oDGvStNGmnj44m8sHg",
            "id": "5Hc9oDGvStNGmnj44m8sHg",
            "name": "Tyler Ward",
            "type": "artist",
            "uri": "spotify:artist:5Hc9oDGvStNGmnj44m8sHg"
          }
        ],
        "available_markets": [
          "AD",
          "AR",
          "AT",
          "AU",
          "BE",
          "BG",
          "BO",
          "BR",
          "CA",
          "CH",
          "CL",
          "CO",
          "CR",
          "CY",
          "CZ",
          "DE",
          "DK",
          "DO",
          "EC",
          "EE",
          "ES",
          "FI",
          "FR",
          "GB",
          "GR",
          "GT",
          "HK",
          "HN",
          "HU",
          "ID",
          "IE",
          "IL",
          "IS",
          "IT",
          "JP",
          "LI",
          "LT",
          "LU",
          "LV",
          "MC",
          "MT",
          "MX",
          "MY",
          "NI",
          "NL",
          "NO",
          "NZ",
          "PA",
          "PE",
          "PH",
          "PL",
          "PT",
          "PY",
          "RO",
          "SE",
          "SG",
          "SK",
          "SV",
          "TH",
          "TR",
          "TW",
          "US",
          "UY",
          "VN",
          "ZA"
        ],
        "disc_number": 1,
        "duration_ms": 144000,
        "explicit": false,
        "external_ids": { "isrc": "GBDMT1500104" },
        "external_urls": {
          "spotify": "https://open.spotify.com/track/4OhQb7W96FuLqMpq2NnVq5"
        },
        "href": "https://api.spotify.com/v1/tracks/4OhQb7W96FuLqMpq2NnVq5",
        "id": "4OhQb7W96FuLqMpq2NnVq5",
        "is_local": false,
        "name": "Shut Up & Dance - Acoustic",
        "popularity": 45,
        "preview_url":
          "https://p.scdn.co/mp3-preview/80389af75a08dd3e2515ac2cd779762e6871df03?cid=cd2cbf7b258249d1b36e316ca7fee072",
        "track_number": 2,
        "type": "track",
        "uri": "spotify:track:4OhQb7W96FuLqMpq2NnVq5"
      },
      {
        "album": {
          "album_type": "album",
          "artists": [
            {
              "external_urls": {
                "spotify":
                  "https://open.spotify.com/artist/7Ey4PD4MYsKc5I2dolUwbH"
              },
              "href":
                "https://api.spotify.com/v1/artists/7Ey4PD4MYsKc5I2dolUwbH",
              "id": "7Ey4PD4MYsKc5I2dolUwbH",
              "name": "Aerosmith",
              "type": "artist",
              "uri": "spotify:artist:7Ey4PD4MYsKc5I2dolUwbH"
            }
          ],
          "available_markets": ["CA", "MX", "US"],
          "external_urls": {
            "spotify": "https://open.spotify.com/album/1tuM8yBePaekEruGsH2J79"
          },
          "href": "https://api.spotify.com/v1/albums/1tuM8yBePaekEruGsH2J79",
          "id": "1tuM8yBePaekEruGsH2J79",
          "images": [
            {
              "height": 640,
              "url":
                "https://i.scdn.co/image/f42de1a4044ccc34256ef9576d713c2c9b8eb7b9",
              "width": 640
            },
            {
              "height": 300,
              "url":
                "https://i.scdn.co/image/a7a3c68141c75d2a51f617a8b62bfae07c3fdfe2",
              "width": 300
            },
            {
              "height": 64,
              "url":
                "https://i.scdn.co/image/e2ae33b359652e7b788198ddc48155fbd94fa332",
              "width": 64
            }
          ],
          "name": "Get A Grip",
          "release_date": "1993-01-01",
          "release_date_precision": "day",
          "type": "album",
          "uri": "spotify:album:1tuM8yBePaekEruGsH2J79"
        },
        "artists": [
          {
            "external_urls": {
              "spotify":
                "https://open.spotify.com/artist/7Ey4PD4MYsKc5I2dolUwbH"
            },
            "href": "https://api.spotify.com/v1/artists/7Ey4PD4MYsKc5I2dolUwbH",
            "id": "7Ey4PD4MYsKc5I2dolUwbH",
            "name": "Aerosmith",
            "type": "artist",
            "uri": "spotify:artist:7Ey4PD4MYsKc5I2dolUwbH"
          }
        ],
        "available_markets": ["CA", "MX", "US"],
        "disc_number": 1,
        "duration_ms": 295250,
        "explicit": false,
        "external_ids": { "isrc": "USIR10000446" },
        "external_urls": {
          "spotify": "https://open.spotify.com/track/3BbWOytu8sLDD2pgU5z5xz"
        },
        "href": "https://api.spotify.com/v1/tracks/3BbWOytu8sLDD2pgU5z5xz",
        "id": "3BbWOytu8sLDD2pgU5z5xz",
        "is_local": false,
        "name": "Shut Up And Dance",
        "popularity": 33,
        "preview_url": null,
        "track_number": 8,
        "type": "track",
        "uri": "spotify:track:3BbWOytu8sLDD2pgU5z5xz"
      },
      {
        "album": {
          "album_type": "single",
          "artists": [
            {
              "external_urls": {
                "spotify":
                  "https://open.spotify.com/artist/4m5tOCn8XenaMpf0yEwTCG"
              },
              "href":
                "https://api.spotify.com/v1/artists/4m5tOCn8XenaMpf0yEwTCG",
              "id": "4m5tOCn8XenaMpf0yEwTCG",
              "name": "Me With Wings",
              "type": "artist",
              "uri": "spotify:artist:4m5tOCn8XenaMpf0yEwTCG"
            }
          ],
          "available_markets": [
            "AD",
            "AR",
            "AT",
            "AU",
            "BE",
            "BG",
            "BO",
            "BR",
            "CA",
            "CH",
            "CL",
            "CO",
            "CR",
            "CY",
            "CZ",
            "DE",
            "DK",
            "DO",
            "EC",
            "EE",
            "ES",
            "FI",
            "FR",
            "GB",
            "GR",
            "GT",
            "HK",
            "HN",
            "HU",
            "ID",
            "IE",
            "IL",
            "IS",
            "IT",
            "JP",
            "LI",
            "LT",
            "LU",
            "LV",
            "MC",
            "MT",
            "MX",
            "MY",
            "NI",
            "NL",
            "NO",
            "NZ",
            "PA",
            "PE",
            "PH",
            "PL",
            "PT",
            "PY",
            "RO",
            "SE",
            "SG",
            "SK",
            "SV",
            "TH",
            "TR",
            "TW",
            "US",
            "UY",
            "VN",
            "ZA"
          ],
          "external_urls": {
            "spotify": "https://open.spotify.com/album/2mEOyKt0AEVxRvgROQ02RY"
          },
          "href": "https://api.spotify.com/v1/albums/2mEOyKt0AEVxRvgROQ02RY",
          "id": "2mEOyKt0AEVxRvgROQ02RY",
          "images": [
            {
              "height": 640,
              "url":
                "https://i.scdn.co/image/f2709eca5f8dc4a8b9b6d92eac51a3c059b87bdc",
              "width": 640
            },
            {
              "height": 300,
              "url":
                "https://i.scdn.co/image/9636ff91fea3bff3b5ca39d140efc0e20860b188",
              "width": 300
            },
            {
              "height": 64,
              "url":
                "https://i.scdn.co/image/99c3252d8fba163cdc5ee29dec940199e85b36e5",
              "width": 64
            }
          ],
          "name": "Shut up and Dance With Me",
          "release_date": "2015-04-01",
          "release_date_precision": "day",
          "type": "album",
          "uri": "spotify:album:2mEOyKt0AEVxRvgROQ02RY"
        },
        "artists": [
          {
            "external_urls": {
              "spotify":
                "https://open.spotify.com/artist/4m5tOCn8XenaMpf0yEwTCG"
            },
            "href": "https://api.spotify.com/v1/artists/4m5tOCn8XenaMpf0yEwTCG",
            "id": "4m5tOCn8XenaMpf0yEwTCG",
            "name": "Me With Wings",
            "type": "artist",
            "uri": "spotify:artist:4m5tOCn8XenaMpf0yEwTCG"
          }
        ],
        "available_markets": [
          "AD",
          "AR",
          "AT",
          "AU",
          "BE",
          "BG",
          "BO",
          "BR",
          "CA",
          "CH",
          "CL",
          "CO",
          "CR",
          "CY",
          "CZ",
          "DE",
          "DK",
          "DO",
          "EC",
          "EE",
          "ES",
          "FI",
          "FR",
          "GB",
          "GR",
          "GT",
          "HK",
          "HN",
          "HU",
          "ID",
          "IE",
          "IL",
          "IS",
          "IT",
          "JP",
          "LI",
          "LT",
          "LU",
          "LV",
          "MC",
          "MT",
          "MX",
          "MY",
          "NI",
          "NL",
          "NO",
          "NZ",
          "PA",
          "PE",
          "PH",
          "PL",
          "PT",
          "PY",
          "RO",
          "SE",
          "SG",
          "SK",
          "SV",
          "TH",
          "TR",
          "TW",
          "US",
          "UY",
          "VN",
          "ZA"
        ],
        "disc_number": 1,
        "duration_ms": 199592,
        "explicit": false,
        "external_ids": { "isrc": "TCACE1596177" },
        "external_urls": {
          "spotify": "https://open.spotify.com/track/2sdZRRy6DSHMkNBQJ4AXco"
        },
        "href": "https://api.spotify.com/v1/tracks/2sdZRRy6DSHMkNBQJ4AXco",
        "id": "2sdZRRy6DSHMkNBQJ4AXco",
        "is_local": false,
        "name": "Shut up and DanceWith Me",
        "popularity": 34,
        "preview_url":
          "https://p.scdn.co/mp3-preview/3b5d007b84d72e2e218fbf881e9f3f0f12f9818a?cid=cd2cbf7b258249d1b36e316ca7fee072",
        "track_number": 1,
        "type": "track",
        "uri": "spotify:track:2sdZRRy6DSHMkNBQJ4AXco"
      },
      {
        "album": {
          "album_type": "album",
          "artists": [
            {
              "external_urls": {
                "spotify":
                  "https://open.spotify.com/artist/6J2Mlo8s6JMsJQr35ulpvI"
              },
              "href":
                "https://api.spotify.com/v1/artists/6J2Mlo8s6JMsJQr35ulpvI",
              "id": "6J2Mlo8s6JMsJQr35ulpvI",
              "name": "Victoria Duffield",
              "type": "artist",
              "uri": "spotify:artist:6J2Mlo8s6JMsJQr35ulpvI"
            }
          ],
          "available_markets": [
            "AD",
            "AR",
            "AT",
            "AU",
            "BE",
            "BG",
            "BO",
            "BR",
            "CA",
            "CH",
            "CL",
            "CO",
            "CR",
            "CY",
            "CZ",
            "DE",
            "DK",
            "DO",
            "EC",
            "EE",
            "ES",
            "FI",
            "FR",
            "GB",
            "GR",
            "GT",
            "HK",
            "HN",
            "HU",
            "ID",
            "IE",
            "IL",
            "IS",
            "IT",
            "JP",
            "LI",
            "LT",
            "LU",
            "LV",
            "MC",
            "MT",
            "MY",
            "NI",
            "NL",
            "NO",
            "NZ",
            "PA",
            "PE",
            "PH",
            "PL",
            "PT",
            "PY",
            "RO",
            "SE",
            "SG",
            "SK",
            "SV",
            "TH",
            "TR",
            "TW",
            "US",
            "UY",
            "VN",
            "ZA"
          ],
          "external_urls": {
            "spotify": "https://open.spotify.com/album/1OQXAyZuB8YZWIWt3CIMpJ"
          },
          "href": "https://api.spotify.com/v1/albums/1OQXAyZuB8YZWIWt3CIMpJ",
          "id": "1OQXAyZuB8YZWIWt3CIMpJ",
          "images": [
            {
              "height": 640,
              "url":
                "https://i.scdn.co/image/811048824b72cf77b55231126253d7bc29564966",
              "width": 640
            },
            {
              "height": 300,
              "url":
                "https://i.scdn.co/image/fe65f7b625c231e733d48a261d1140eab2b289ab",
              "width": 300
            },
            {
              "height": 64,
              "url":
                "https://i.scdn.co/image/40f191a73d87ca5703b2807a711551758834cf88",
              "width": 64
            }
          ],
          "name": "Shut Up And Dance",
          "release_date": "2012-06-26",
          "release_date_precision": "day",
          "type": "album",
          "uri": "spotify:album:1OQXAyZuB8YZWIWt3CIMpJ"
        },
        "artists": [
          {
            "external_urls": {
              "spotify":
                "https://open.spotify.com/artist/6J2Mlo8s6JMsJQr35ulpvI"
            },
            "href": "https://api.spotify.com/v1/artists/6J2Mlo8s6JMsJQr35ulpvI",
            "id": "6J2Mlo8s6JMsJQr35ulpvI",
            "name": "Victoria Duffield",
            "type": "artist",
            "uri": "spotify:artist:6J2Mlo8s6JMsJQr35ulpvI"
          },
          {
            "external_urls": {
              "spotify":
                "https://open.spotify.com/artist/79Xp2rRN7wdsaTJgttdX3K"
            },
            "href": "https://api.spotify.com/v1/artists/79Xp2rRN7wdsaTJgttdX3K",
            "id": "79Xp2rRN7wdsaTJgttdX3K",
            "name": "Cody Simpson",
            "type": "artist",
            "uri": "spotify:artist:79Xp2rRN7wdsaTJgttdX3K"
          }
        ],
        "available_markets": [
          "AD",
          "AR",
          "AT",
          "AU",
          "BE",
          "BG",
          "BO",
          "BR",
          "CA",
          "CH",
          "CL",
          "CO",
          "CR",
          "CY",
          "CZ",
          "DE",
          "DK",
          "DO",
          "EC",
          "EE",
          "ES",
          "FI",
          "FR",
          "GB",
          "GR",
          "GT",
          "HK",
          "HN",
          "HU",
          "ID",
          "IE",
          "IL",
          "IS",
          "IT",
          "JP",
          "LI",
          "LT",
          "LU",
          "LV",
          "MC",
          "MT",
          "MY",
          "NI",
          "NL",
          "NO",
          "NZ",
          "PA",
          "PE",
          "PH",
          "PL",
          "PT",
          "PY",
          "RO",
          "SE",
          "SG",
          "SK",
          "SV",
          "TH",
          "TR",
          "TW",
          "US",
          "UY",
          "VN",
          "ZA"
        ],
        "disc_number": 1,
        "duration_ms": 192880,
        "explicit": false,
        "external_ids": { "isrc": "CAW111200147" },
        "external_urls": {
          "spotify": "https://open.spotify.com/track/6WxmudrP1QefUQPcxbqTmO"
        },
        "href": "https://api.spotify.com/v1/tracks/6WxmudrP1QefUQPcxbqTmO",
        "id": "6WxmudrP1QefUQPcxbqTmO",
        "is_local": false,
        "name": "They Don't Know About Us (feat. Cody Simpson)",
        "popularity": 38,
        "preview_url":
          "https://p.scdn.co/mp3-preview/332cf38b290e07ce2d0e0c329ac8002e080a8abe?cid=cd2cbf7b258249d1b36e316ca7fee072",
        "track_number": 3,
        "type": "track",
        "uri": "spotify:track:6WxmudrP1QefUQPcxbqTmO"
      },
      {
        "album": {
          "album_type": "album",
          "artists": [
            {
              "external_urls": {
                "spotify":
                  "https://open.spotify.com/artist/5BKzvAPtNXnt0LwzGvKOH3"
              },
              "href":
                "https://api.spotify.com/v1/artists/5BKzvAPtNXnt0LwzGvKOH3",
              "id": "5BKzvAPtNXnt0LwzGvKOH3",
              "name": "Aaron Watson",
              "type": "artist",
              "uri": "spotify:artist:5BKzvAPtNXnt0LwzGvKOH3"
            }
          ],
          "available_markets": ["CA", "US"],
          "external_urls": {
            "spotify": "https://open.spotify.com/album/0JLxbOIxLJ5oDqYLOxJlnM"
          },
          "href": "https://api.spotify.com/v1/albums/0JLxbOIxLJ5oDqYLOxJlnM",
          "id": "0JLxbOIxLJ5oDqYLOxJlnM",
          "images": [
            {
              "height": 640,
              "url":
                "https://i.scdn.co/image/8fe4b2d28e543128ccc13a7a2327f4f445963972",
              "width": 640
            },
            {
              "height": 300,
              "url":
                "https://i.scdn.co/image/330799dec4e7347e2d651a60cdbc8ac41c219d4c",
              "width": 300
            },
            {
              "height": 64,
              "url":
                "https://i.scdn.co/image/b8585a90df8e4067331a69cea7a775525f35795d",
              "width": 64
            }
          ],
          "name": "Shut up and Dance",
          "release_date": "2002",
          "release_date_precision": "year",
          "type": "album",
          "uri": "spotify:album:0JLxbOIxLJ5oDqYLOxJlnM"
        },
        "artists": [
          {
            "external_urls": {
              "spotify":
                "https://open.spotify.com/artist/5BKzvAPtNXnt0LwzGvKOH3"
            },
            "href": "https://api.spotify.com/v1/artists/5BKzvAPtNXnt0LwzGvKOH3",
            "id": "5BKzvAPtNXnt0LwzGvKOH3",
            "name": "Aaron Watson",
            "type": "artist",
            "uri": "spotify:artist:5BKzvAPtNXnt0LwzGvKOH3"
          }
        ],
        "available_markets": ["CA", "US"],
        "disc_number": 1,
        "duration_ms": 243840,
        "explicit": false,
        "external_ids": { "isrc": "US4AB0400008" },
        "external_urls": {
          "spotify": "https://open.spotify.com/track/3NkjSaA6gBQoDUutcpdgfD"
        },
        "href": "https://api.spotify.com/v1/tracks/3NkjSaA6gBQoDUutcpdgfD",
        "id": "3NkjSaA6gBQoDUutcpdgfD",
        "is_local": false,
        "name": "Wish I Could Say I'd Been Drinking",
        "popularity": 30,
        "preview_url":
          "https://p.scdn.co/mp3-preview/0b3b07b97cd4af584cfd2b816e2cf84bcbb944a7?cid=cd2cbf7b258249d1b36e316ca7fee072",
        "track_number": 8,
        "type": "track",
        "uri": "spotify:track:3NkjSaA6gBQoDUutcpdgfD"
      },
      {
        "album": {
          "album_type": "compilation",
          "artists": [
            {
              "external_urls": {
                "spotify":
                  "https://open.spotify.com/artist/0LyfQWJT6nXafLPZqxe9Of"
              },
              "href":
                "https://api.spotify.com/v1/artists/0LyfQWJT6nXafLPZqxe9Of",
              "id": "0LyfQWJT6nXafLPZqxe9Of",
              "name": "Various Artists",
              "type": "artist",
              "uri": "spotify:artist:0LyfQWJT6nXafLPZqxe9Of"
            }
          ],
          "available_markets": [
            "AD",
            "AR",
            "AT",
            "AU",
            "BE",
            "BG",
            "BO",
            "BR",
            "CA",
            "CH",
            "CL",
            "CO",
            "CR",
            "CY",
            "CZ",
            "DE",
            "DK",
            "DO",
            "EC",
            "EE",
            "ES",
            "FI",
            "FR",
            "GB",
            "GR",
            "GT",
            "HK",
            "HN",
            "HU",
            "ID",
            "IE",
            "IL",
            "IS",
            "IT",
            "JP",
            "LI",
            "LT",
            "LU",
            "LV",
            "MC",
            "MT",
            "MX",
            "MY",
            "NI",
            "NL",
            "NO",
            "NZ",
            "PA",
            "PE",
            "PH",
            "PL",
            "PT",
            "PY",
            "RO",
            "SE",
            "SG",
            "SK",
            "SV",
            "TH",
            "TR",
            "TW",
            "US",
            "UY",
            "VN",
            "ZA"
          ],
          "external_urls": {
            "spotify": "https://open.spotify.com/album/6Z0524mJfaVNkvsN2zmOzG"
          },
          "href": "https://api.spotify.com/v1/albums/6Z0524mJfaVNkvsN2zmOzG",
          "id": "6Z0524mJfaVNkvsN2zmOzG",
          "images": [
            {
              "height": 640,
              "url":
                "https://i.scdn.co/image/b109fc01a949061b5e7802a5295478b9e1f55cae",
              "width": 640
            },
            {
              "height": 300,
              "url":
                "https://i.scdn.co/image/25ec95d40a3806df94a8455ee01bf265361a9072",
              "width": 300
            },
            {
              "height": 64,
              "url":
                "https://i.scdn.co/image/a0f1ce66df4331b48267266b841d590a8fe71f2d",
              "width": 64
            }
          ],
          "name": "Got You Covered, Vol. 1",
          "release_date": "2017-02-24",
          "release_date_precision": "day",
          "type": "album",
          "uri": "spotify:album:6Z0524mJfaVNkvsN2zmOzG"
        },
        "artists": [
          {
            "external_urls": {
              "spotify":
                "https://open.spotify.com/artist/3pRHJe6zzi3Rq180D1H2JM"
            },
            "href": "https://api.spotify.com/v1/artists/3pRHJe6zzi3Rq180D1H2JM",
            "id": "3pRHJe6zzi3Rq180D1H2JM",
            "name": "Heroes Like Villains",
            "type": "artist",
            "uri": "spotify:artist:3pRHJe6zzi3Rq180D1H2JM"
          }
        ],
        "available_markets": [
          "AD",
          "AR",
          "AT",
          "AU",
          "BE",
          "BG",
          "BO",
          "BR",
          "CA",
          "CH",
          "CL",
          "CO",
          "CR",
          "CY",
          "CZ",
          "DE",
          "DK",
          "DO",
          "EC",
          "EE",
          "ES",
          "FI",
          "FR",
          "GB",
          "GR",
          "GT",
          "HK",
          "HN",
          "HU",
          "ID",
          "IE",
          "IL",
          "IS",
          "IT",
          "JP",
          "LI",
          "LT",
          "LU",
          "LV",
          "MC",
          "MT",
          "MX",
          "MY",
          "NI",
          "NL",
          "NO",
          "NZ",
          "PA",
          "PE",
          "PH",
          "PL",
          "PT",
          "PY",
          "RO",
          "SE",
          "SG",
          "SK",
          "SV",
          "TH",
          "TR",
          "TW",
          "US",
          "UY",
          "VN",
          "ZA"
        ],
        "disc_number": 1,
        "duration_ms": 192339,
        "explicit": false,
        "external_ids": { "isrc": "QMMUK1700486" },
        "external_urls": {
          "spotify": "https://open.spotify.com/track/3CxsmzPfKR6K8PfOssHVT5"
        },
        "href": "https://api.spotify.com/v1/tracks/3CxsmzPfKR6K8PfOssHVT5",
        "id": "3CxsmzPfKR6K8PfOssHVT5",
        "is_local": false,
        "name": "Shut Up & Dance",
        "popularity": 33,
        "preview_url":
          "https://p.scdn.co/mp3-preview/43ee8ae6f8895e6ebabe55f15af27da851ca4188?cid=cd2cbf7b258249d1b36e316ca7fee072",
        "track_number": 6,
        "type": "track",
        "uri": "spotify:track:3CxsmzPfKR6K8PfOssHVT5"
      }
    ],
    "limit": 20,
    "next":
      "https://api.spotify.com/v1/search?query=shut+up+and+dance&type=track&offset=20&limit=20",
    "offset": 0,
    "previous": null,
    "total": 1240
  }
}
